spiderkeeper_deploy/__init__.py
spiderkeeper_deploy/__main__.py
spiderkeeper_deploy/cli.py
spiderkeeper_deploy-0.1.2.dist-info/METADATA
spiderkeeper_deploy-0.1.2.dist-info/RECORD
spiderkeeper_deploy-0.1.2.dist-info/WHEEL
spiderkeeper_deploy-0.1.2.dist-info/entry_points.txt
spiderkeeper_deploy-0.1.2.dist-info/top_level.txt
tutorial/__init__.py
tutorial/items.py
tutorial/middlewares.py
tutorial/pipelines.py
tutorial/settings.py
tutorial/spiders/__init__.py
tutorial/spiders/quotes_spider.py
