Metadata-Version: 2.1
Name: spiderkeeper-deploy
Version: 0.1.2
Summary: Deploy to SpiderKeeper
Home-page: https://github.com/StoicPerlman/spiderkeeper-deploy
Author: Sam Kleiner
Author-email: sam@skleiner.com
License: MIT license
Download-URL: https://github.com/StoicPerlman/spiderkeeper-deploy/archive/0.1.2.tar.gz
Keywords: spiderkeeper,scrapy,devops
Platform: UNKNOWN
Classifier: Development Status :: 5 - Production/Stable
Classifier: Intended Audience :: Developers
Classifier: License :: OSI Approved :: MIT License
Classifier: Operating System :: Unix
Classifier: Operating System :: POSIX
Classifier: Operating System :: Microsoft :: Windows
Classifier: Programming Language :: Python
Classifier: Programming Language :: Python :: 3.6
Classifier: Programming Language :: Python :: 3.7
Classifier: Programming Language :: Python :: Implementation :: CPython
Classifier: Programming Language :: Python :: Implementation :: PyPy
Classifier: Topic :: Utilities
Requires-Dist: click
Requires-Dist: configparser
Requires-Dist: requests
Requires-Dist: scrapy
